square_database/__init__.py
square_database/configuration.py
square_database/data/config.sample.ini
square_database/data/config.testing.sample.ini
square_database/main.py
square_database/messages.py
square_database/models/__init__.py
square_database/models/core.py
square_database/routes/__init__.py
square_database/routes/core.py
square_database/utils/__init__.py
square_database/utils/common_operations.py
square_database/utils/routes/__init__.py
square_database/utils/routes/core.py
square_database-3.4.0.dist-info/WHEEL
square_database-3.4.0.dist-info/METADATA
square_database-3.4.0.dist-info/RECORD
